monitor/.env.example
monitor/Dockerfile
monitor/README.md
monitor/__init__.py
monitor/docker-compose.ghcr.yml
monitor/docker-compose.yml
monitor/requirements.txt
monitor/shellhorn_monitor.py
monitor/test_notifications.py
shellhorn/__init__.py
shellhorn/cli.py
shellhorn/config.py
shellhorn/core.py
shellhorn/notifiers.py
shellhorn-1.0.0.dist-info/licenses/LICENSE
shellhorn-1.0.0.dist-info/METADATA
shellhorn-1.0.0.dist-info/WHEEL
shellhorn-1.0.0.dist-info/entry_points.txt
shellhorn-1.0.0.dist-info/top_level.txt
shellhorn-1.0.0.dist-info/RECORD
