Metadata-Version: 2.4
Name: shellhorn
Version: 1.0.0
Summary: 🐚📯 A lightweight command wrapper that sounds the horn when your shell commands complete, fail, or die unexpectedly
Author: Mitchell Currie
License: MIT
Project-URL: Homepage, https://github.com/mitchins/shellhorn
Project-URL: Repository, https://github.com/mitchins/shellhorn
Project-URL: Issues, https://github.com/mitchins/shellhorn/issues
Keywords: shell,command,wrapper,notification,monitoring,mqtt,pushover
Classifier: Development Status :: 5 - Production/Stable
Classifier: Environment :: Console
Classifier: Intended Audience :: Developers
Classifier: Intended Audience :: System Administrators
Classifier: License :: OSI Approved :: MIT License
Classifier: Operating System :: OS Independent
Classifier: Programming Language :: Python :: 3
Classifier: Programming Language :: Python :: 3.10
Classifier: Programming Language :: Python :: 3.11
Classifier: Programming Language :: Python :: 3.12
Classifier: Topic :: System :: Monitoring
Classifier: Topic :: System :: Shells
Classifier: Topic :: Utilities
Requires-Python: >=3.10
License-File: LICENSE
Requires-Dist: paho-mqtt>=1.6.0
Requires-Dist: requests>=2.25.0
Requires-Dist: PyYAML>=6.0
Provides-Extra: dev
Requires-Dist: pytest>=6.0; extra == "dev"
Requires-Dist: pytest-cov; extra == "dev"
Requires-Dist: black; extra == "dev"
Requires-Dist: flake8; extra == "dev"
Requires-Dist: flake8-bugbear; extra == "dev"
Requires-Dist: vulture; extra == "dev"
Requires-Dist: bandit; extra == "dev"
Requires-Dist: safety; extra == "dev"
Dynamic: license-file
